kyutils/__init__.py
kyutils/behavior/__init__.py
kyutils/behavior/position.py
kyutils/behavior/reward.py
kyutils/behavior/track.py
kyutils/decoding/__init__.py
kyutils/decoding/figurl.py
kyutils/decoding/utils.py
kyutils/nwb/__init__.py
kyutils/nwb/conversion.py
kyutils/nwb/utils.py
kyutils/probe/Rice_EBL_128ch_1s.csv
kyutils/probe/__init__.py
kyutils/probe/generate_probe.py
kyutils/spikegadgets/__init__.py
kyutils/spikegadgets/header.py
kyutils/spikegadgets/reconfig.py
kyutils/spikegadgets/spike_config_15.xml
kyutils/spikegadgets/spike_config_20.xml
kyutils/spikegadgets/spike_config_32tet.xml
kyutils/spikegadgets/trode_conf_base.xml
kyutils/spikegadgets/trodesconf.py
kyutils/spikesorting/__init__.py
kyutils/spikesorting/analysis.py
kyutils/spikesorting/figurl.py
kyutils/spikesorting/metrics.py
kyutils/spikesorting/waveform.py
kyutils-0.1.121.dist-info/METADATA
kyutils-0.1.121.dist-info/WHEEL
kyutils-0.1.121.dist-info/licenses/LICENSE
kyutils-0.1.121.dist-info/RECORD
