Metadata-Version: 2.4
Name: kyutils
Version: 0.1.121
Summary: kyu's utils
License: MIT
License-File: LICENSE
Author: Kyu Hyun Lee
Author-email: kyuhyun9056@gmail.com
Requires-Python: >=3.9,<3.14
Classifier: License :: OSI Approved :: MIT License
Classifier: Programming Language :: Python :: 3
Classifier: Programming Language :: Python :: 3.9
Classifier: Programming Language :: Python :: 3.10
Classifier: Programming Language :: Python :: 3.11
Classifier: Programming Language :: Python :: 3.12
Classifier: Programming Language :: Python :: 3.13
Provides-Extra: decoder
Provides-Extra: figurl
Provides-Extra: nwb
Requires-Dist: hdmf (==3.13.0) ; extra == "nwb"
Requires-Dist: kachery_cloud (==0.4.8) ; extra == "figurl"
Requires-Dist: matplotlib (>3.7.2)
Requires-Dist: numpy (>1.24.0)
Requires-Dist: position_tools (==0.1.0.dev0) ; extra == "decoder"
Requires-Dist: probeinterface (>0.2.17)
Requires-Dist: pynwb (==2.6.0) ; extra == "nwb"
Requires-Dist: replay_trajectory_classification (==1.3.15) ; extra == "decoder"
Requires-Dist: ripple_detection (==1.4.0) ; extra == "decoder"
Requires-Dist: scikit-learn (>=1.0.1,<2.0.0)
Requires-Dist: scipy (>=1.7.1,<2.0.0)
Requires-Dist: sortingview (==0.13.2) ; extra == "figurl"
Requires-Dist: spikeinterface (>0.99) ; python_version < "3.14"
Requires-Dist: track_linearization (==2.3.1) ; extra == "decoder"
Requires-Dist: trajectory_analysis_tools (==1.1.0) ; extra == "decoder"
